[  
    {  
      "key":"육군",
      "values":[  
        {  
          "axis":"팔굽혀펴기",
          "key":"육군",
          "value":3
        },
        {  
          "axis":"윗몸일으키기",
          "key":"육군",
          "value":3.2
        },
        {  
          "axis":"3Km 달리기",
          "key":"육군",
          "value":4
        }
      ]
    },
    {  
      "key":"해군",
      "values":[  
        {  
          "axis":"팔굽혀펴기",
          "key":"해군",
          "value":4
        },
        {  
          "axis":"윗몸일으키기",
          "key":"해군",
          "value":3.5
        },
        {  
          "axis":"3Km 달리기",
          "key":"해군",
          "value":3.5
        }
      ]
    },
    {  
      "key":"공군",
      "values":[  
        {  
          "axis":"팔굽혀펴기",
          "key":"공군",
          "value":2.7
        },
        {  
          "axis":"윗몸일으키기",
          "key":"공군",
          "value":2.7
        },
        {  
          "axis":"3Km 달리기",
          "key":"공군",
          "value":1
        }
      ]
    }
  ]